dccp/__init__.py
dccp/constraint.py
dccp/linearize.py
dccp/objective.py
dccp/problem.py
dccp-1.0.5.dist-info/METADATA
dccp-1.0.5.dist-info/WHEEL
dccp-1.0.5.dist-info/top_level.txt
dccp-1.0.5.dist-info/RECORD
